ksp_sample/__init__.py
ksp_sample/version.prop
ksp_sample-0.0.6.dist-info/DESCRIPTION.rst
ksp_sample-0.0.6.dist-info/METADATA
ksp_sample-0.0.6.dist-info/RECORD
ksp_sample-0.0.6.dist-info/WHEEL
ksp_sample-0.0.6.dist-info/entry_points.txt
ksp_sample-0.0.6.dist-info/metadata.json
ksp_sample-0.0.6.dist-info/top_level.txt
