Metadata-Version: 2.0
Name: ksp-sample
Version: 0.0.6
Summary: Project Short Description
Home-page: https://github.com/TheFriendlyCoder/ksp_sample
Author: Kevin S. Phillips
Author-email: thefriendlycoder@gmail.com
License: GPL
Keywords: space separated tags
Platform: UNKNOWN
Classifier: Development Status :: 3 - Alpha
Classifier: Environment :: Console
Classifier: License :: OSI Approved :: GNU General Public License v3 or later (GPLv3+)
Classifier: Topic :: Software Development :: Libraries
Classifier: Natural Language :: English
Classifier: Operating System :: OS Independent
Classifier: Programming Language :: Python :: 2
Classifier: Programming Language :: Python :: 3
Requires-Python: >=2.7, !=3.0.*, !=3.1.*, !=3.2.*, !=3.3.*, <4
Requires-Dist: six
Provides-Extra: dev
Requires-Dist: twine; extra == 'dev'
Requires-Dist: pytest; extra == 'dev'
Requires-Dist: pytest-cov; extra == 'dev'
Requires-Dist: mock; extra == 'dev'
Requires-Dist: pylint; extra == 'dev'
Requires-Dist: sphinx; extra == 'dev'
Requires-Dist: tox; extra == 'dev'
